WeikeNuoCcnaCcnpShiyanShouceV12Fix1/README.md
WeikeNuoCcnaCcnpShiyanShouceV12Fix1/__init__.py
WeikeNuoCcnaCcnpShiyanShouceV12Fix1/__main__.py
WeikeNuoCcnaCcnpShiyanShouceV12Fix1/file.pdf
WeikeNuoCcnaCcnpShiyanShouceV12Fix1/index.html
weike_nuo_ccna_ccnp_shiyan_shouce_v1_2_fix1-2025.3.25.1.dist-info/METADATA
weike_nuo_ccna_ccnp_shiyan_shouce_v1_2_fix1-2025.3.25.1.dist-info/WHEEL
weike_nuo_ccna_ccnp_shiyan_shouce_v1_2_fix1-2025.3.25.1.dist-info/entry_points.txt
weike_nuo_ccna_ccnp_shiyan_shouce_v1_2_fix1-2025.3.25.1.dist-info/top_level.txt
weike_nuo_ccna_ccnp_shiyan_shouce_v1_2_fix1-2025.3.25.1.dist-info/RECORD
